graphbridge/__init__.py
graphbridge/graph_bridge.py
graphbridge-0.0.5.dist-info/licenses/LICENCE
graphbridge-0.0.5.dist-info/METADATA
graphbridge-0.0.5.dist-info/WHEEL
graphbridge-0.0.5.dist-info/top_level.txt
graphbridge-0.0.5.dist-info/RECORD
