Metadata-Version: 2.4
Name: graphbridge
Version: 0.0.5
Summary: GraphBridge is a lightweight Microsoft Graph client that uses app-only (Azure AD) authentication and streamlines SharePoint site/list operations: metadata retrieval, feature-based queries, CRUD, upsert, and field key encoding/decoding.
Author-email: Cecchelani Diego <ceccdieg@gmail.com>
License-Expression: MIT
Project-URL: Homepage, https://www
Project-URL: Issues, https://www
Classifier: Development Status :: 2 - Pre-Alpha
Classifier: Programming Language :: Python :: 3
Classifier: Operating System :: OS Independent
Requires-Python: >=3.10
License-File: LICENCE
Requires-Dist: azure-identity==1.24.0
Requires-Dist: requests==2.32.5
Dynamic: license-file
